__init__.py
netmiko/__init__.py
netmiko/base_connection.py
netmiko/channel.py
netmiko/cisco_base_connection.py
netmiko/exceptions.py
netmiko/netmiko_globals.py
netmiko/no_config.py
netmiko/no_enable.py
netmiko/scp_functions.py
netmiko/scp_handler.py
netmiko/session_log.py
netmiko/snmp_autodetect.py
netmiko/ssh_auth.py
netmiko/ssh_autodetect.py
netmiko/ssh_dispatcher.py
netmiko/utilities.py
netmiko/a10/__init__.py
netmiko/a10/a10_ssh.py
netmiko/accedian/__init__.py
netmiko/accedian/accedian_ssh.py
netmiko/adtran/__init__.py
netmiko/adtran/adtran.py
netmiko/adva/__init__.py
netmiko/adva/adva_aos_fsp_150_f2.py
netmiko/adva/adva_aos_fsp_150_f3.py
netmiko/alcatel/__init__.py
netmiko/alcatel/alcatel_aos_ssh.py
netmiko/allied_telesis/__init__.py
netmiko/allied_telesis/allied_telesis_awplus.py
netmiko/apresia/__init__.py
netmiko/apresia/apresia_aeos.py
netmiko/arista/__init__.py
netmiko/arista/arista.py
netmiko/arris/__init__.py
netmiko/arris/arris_cer.py
netmiko/aruba/__init__.py
netmiko/aruba/aruba_ssh.py
netmiko/audiocode/__init__.py
netmiko/audiocode/audiocode_ssh.py
netmiko/broadcom/__init__.py
netmiko/broadcom/broadcom_icos_ssh.py
netmiko/brocade/__init__.py
netmiko/brocade/brocade_fos_ssh.py
netmiko/calix/__init__.py
netmiko/calix/calix_b6.py
netmiko/casa/__init__.py
netmiko/casa/casa_cmts.py
netmiko/cdot/__init__.py
netmiko/cdot/cdot_cros_ssh.py
netmiko/centec/__init__.py
netmiko/centec/centec_os.py
netmiko/checkpoint/__init__.py
netmiko/checkpoint/checkpoint_gaia_ssh.py
netmiko/ciena/__init__.py
netmiko/ciena/ciena_saos.py
netmiko/cisco/__init__.py
netmiko/cisco/cisco_asa_ssh.py
netmiko/cisco/cisco_ftd_ssh.py
netmiko/cisco/cisco_ios.py
netmiko/cisco/cisco_nxos_ssh.py
netmiko/cisco/cisco_s200.py
netmiko/cisco/cisco_s300.py
netmiko/cisco/cisco_tp_tcce.py
netmiko/cisco/cisco_viptela.py
netmiko/cisco/cisco_wlc_ssh.py
netmiko/cisco/cisco_xr.py
netmiko/citrix/__init__.py
netmiko/citrix/netscaler_ssh.py
netmiko/cli_tools/__init__.py
netmiko/cli_tools/netmiko_cfg.py
netmiko_mishki-4.2.0.1.dist-info/LICENSE
netmiko_mishki-4.2.0.1.dist-info/METADATA
netmiko_mishki-4.2.0.1.dist-info/WHEEL
netmiko_mishki-4.2.0.1.dist-info/top_level.txt
netmiko_mishki-4.2.0.1.dist-info/RECORD
