Metadata-Version: 2.1
Name: netmiko-mishki
Version: 4.2.0.1
Summary: modded netmiko 4.2.0 with lancom and edgecore support for internal use
Author-email: Jochen Mälzer <mishki@mishki.de>
Classifier: Programming Language :: Python :: 3
Classifier: License :: OSI Approved :: MIT License
Classifier: Operating System :: OS Independent
Requires-Python: >=3.7
License-File: LICENSE
Requires-Dist: paramiko >=2.9.5
Requires-Dist: scp >=0.13.6
Requires-Dist: pyyaml >=5.3
Requires-Dist: textfsm >=1.1.3
Requires-Dist: ntc-templates >=2.0.0
Requires-Dist: pyserial >=3.3
Requires-Dist: tenacity
